[
    {
        "year": 2017,
        "data": [
            {
                "name": "农林牧渔",
                "value": 36504
            },
            {
                "name": "采矿业",
                "value": 69500
            },
            {
                "name": "制造业",
                "value": 59470
            },
            {
                "name": "电气水供应业",
                "value": 90348
            },
            {
                "name": "建筑业",
                "value": 55568
            },
            {
                "name": "交通运输，仓储和邮政业",
                "value": 80225
            },
            {
                "name": "IT",
                "value": 133150
            },
            {
                "name": "批发和零售业",
                "value": 71201
            },
            {
                "name": "住宿和餐饮业",
                "value": 45751
            },
            {
                "name": "金融业",
                "value": 122851
            },
            {
                "name": "房地产业",
                "value": 69277
            },
            {
                "name": "租赁和商务服务业",
                "value": 81393
            },
            {
                "name": "科研和技术服务业",
                "value": 107815
            },
            {
                "name": "水利，环境和公共设施管理",
                "value": 52229
            },
            {
                "name": "服务业",
                "value": 50552
            },
            {
                "name": "教育",
                "value": 83412
            },
            {
                "name": "医疗卫生",
                "value": 89648
            },
            {
                "name": "文娱",
                "value": 87803
            },
            {
                "name": "公共管理和社会组织",
                "value": 80372
            }
        ]
    },
    {
        "year":2018,
        "data": [
            {
                "name": "农林牧渔",
                "value": 36466
            },
            {
                "name": "采矿业",
                "value": 81429
            },
            {
                "name": "制造业",
                "value": 72088
            },
            {
                "name": "电气水供应业",
                "value": 100162
            },
            {
                "name": "建筑业",
                "value": 60501
            },
            {
                "name": "交通运输，仓储和邮政业",
                "value": 88508
            },
            {
                "name": "IT",
                "value": 147678
            },
            {
                "name": "批发和零售业",
                "value": 80551
            },
            {
                "name": "住宿和餐饮业",
                "value": 48260
            },
            {
                "name": "金融业",
                "value": 129837
            },
            {
                "name": "房地产业",
                "value": 75281
            },
            {
                "name": "租赁和商务服务业",
                "value": 85147
            },
            {
                "name": "科研和技术服务业",
                "value": 123343
            },
            {
                "name": "水利，环境和公共设施管理",
                "value": 56670
            },
            {
                "name": "服务业",
                "value": 55343
            },
            {
                "name": "教育",
                "value": 92283
            },
            {
                "name": "医疗卫生",
                "value": 98118
            },
            {
                "name": "文娱",
                "value": 98621
            },
            {
                "name": "公共管理和社会组织",
                "value": 87932
            }
        ]
    },
    {
        "year":2019,
        "data": [
            {
                "name": "农林牧渔",
                "value": 39340
            },
            {
                "name": "采矿业",
                "value": 91068
            },
            {
                "name": "制造业",
                "value": 78147
            },
            {
                "name": "电气水供应业",
                "value": 107733
            },
            {
                "name": "建筑业",
                "value": 65580
            },
            {
                "name": "交通运输，仓储和邮政业",
                "value": 97050
            },
            {
                "name": "IT",
                "value": 161352
            },
            {
                "name": "批发和零售业",
                "value": 89047
            },
            {
                "name": "住宿和餐饮业",
                "value": 50346
            },
            {
                "name": "金融业",
                "value": 131405
            },
            {
                "name": "房地产业",
                "value": 80157
            },
            {
                "name": "租赁和商务服务业",
                "value": 88190
            },
            {
                "name": "科研和技术服务业",
                "value": 133459
            },
            {
                "name": "水利，环境和公共设施管理",
                "value": 61158
            },
            {
                "name": "服务业",
                "value": 60232
            },
            {
                "name": "教育",
                "value": 97681
            },
            {
                "name": "医疗卫生",
                "value": 108903
            },
            {
                "name": "文娱",
                "value": 107708
            },
            {
                "name": "公共管理和社会组织",
                "value": 94369
            }
        ]
    },
    {
        "year":2020,
        "data": [
            {
                "name": "农林牧渔",
                "value": 48540
            },
            {
                "name": "采矿业",
                "value": 96674
            },
            {
                "name": "制造业",
                "value": 82783
            },
            {
                "name": "电气水供应业",
                "value": 116728
            },
            {
                "name": "建筑业",
                "value": 69986
            },
            {
                "name": "交通运输，仓储和邮政业",
                "value": 100642
            },
            {
                "name": "IT",
                "value": 177544
            },
            {
                "name": "批发和零售业",
                "value": 96521
            },
            {
                "name": "住宿和餐饮业",
                "value": 48833
            },
            {
                "name": "金融业",
                "value": 133390
            },
            {
                "name": "房地产业",
                "value": 83807
            },
            {
                "name": "租赁和商务服务业",
                "value": 92924
            },
            {
                "name": "科研和技术服务业",
                "value": 139851
            },
            {
                "name": "水利，环境和公共设施管理",
                "value": 63914
            },
            {
                "name": "服务业",
                "value": 60722
            },
            {
                "name": "教育",
                "value": 106474
            },
            {
                "name": "医疗卫生",
                "value": 115449
            },
            {
                "name": "文娱",
                "value": 112081
            },
            {
                "name": "公共管理和社会组织",
                "value": 104487
            }
        ]
    },
    {
        "year":2021,
        "data": [
            {
                "name": "农林牧渔",
                "value": 53819
            },
            {
                "name": "采矿业",
                "value": 108467
            },
            {
                "name": "制造业",
                "value": 92459
            },
            {
                "name": "电气水供应业",
                "value": 125332
            },
            {
                "name": "建筑业",
                "value": 75762
            },
            {
                "name": "交通运输，仓储和邮政业",
                "value": 109851
            },
            {
                "name": "IT",
                "value": 201506
            },
            {
                "name": "批发和零售业",
                "value": 107735
            },
            {
                "name": "住宿和餐饮业",
                "value": 53631
            },
            {
                "name": "金融业",
                "value": 150843
            },
            {
                "name": "房地产业",
                "value": 91143
            },
            {
                "name": "租赁和商务服务业",
                "value": 102537
            },
            {
                "name": "科研和技术服务业",
                "value": 151776
            },
            {
                "name": "水利，环境和公共设施管理",
                "value": 65802
            },
            {
                "name": "服务业",
                "value": 65193
            },
            {
                "name": "教育",
                "value": 111392
            },
            {
                "name": "医疗卫生",
                "value": 126828
            },
            {
                "name": "文娱",
                "value": 117329
            },
            {
                "name": "公共管理和社会组织",
                "value": 111361
            }
        ]
    }
]
